firmetix/__init__.py
firmetix/firmetix.py
firmetix/private_constants.py
firmetix-7.1.2.dist-info/METADATA
firmetix-7.1.2.dist-info/WHEEL
firmetix-7.1.2.dist-info/top_level.txt
firmetix-7.1.2.dist-info/RECORD
