Metadata-Version: 2.1
Name: firmetix
Version: 7.1.2
Summary: Remotely Control And Monitor Arduino and Esp devices
Home-page: https://github.com/Nilon123456789/firmetix
Download-URL: https://github.com/Nilon123456789/firmetix
Author: Nils Lahaye
Author-email: nils.lahaye@icloud.com
Keywords: firmetix,Arduino,Protocol,Python
Classifier: Development Status :: 5 - Production/Stable
Classifier: Environment :: Other Environment
Classifier: Intended Audience :: Developers
Classifier: Intended Audience :: Education
Classifier: License :: OSI Approved :: GNU Affero General Public License v3 or later (AGPLv3+)
Classifier: Operating System :: OS Independent
Classifier: Programming Language :: Python :: 3.7
Classifier: Programming Language :: Python :: 3.8
Classifier: Topic :: Software Development :: Libraries :: Python Modules
Requires-Dist: pyserial
Requires-Dist: simplepyble
